actfw_core/__init__.py
actfw_core/_private/agent_app_protocol/__init__.py
actfw_core/_private/agent_app_protocol/service_server.py
actfw_core/_private/compat/queue.py
actfw_core/_private/schema/agent_app_protocol.py
actfw_core/_private/util/result.py
actfw_core/_private/util/thread.py
actfw_core/application.py
actfw_core/autofocus.py
actfw_core/capture.py
actfw_core/command_server.py
actfw_core/data/LICENSE.txt
actfw_core/data/README.md
actfw_core/data/imx219.json
actfw_core/data/imx708.json
actfw_core/data/imx708_wide.json
actfw_core/data/ov5647.json
actfw_core/libcamera_capture.py
actfw_core/linux/__init__.py
actfw_core/linux/dma_heap.py
actfw_core/linux/ioctl.py
actfw_core/linux/types.py
actfw_core/local_video_server.py
actfw_core/py.typed
actfw_core/schema/agent_app_protocol.py
actfw_core/service_client.py
actfw_core/system.py
actfw_core/task/__init__.py
actfw_core/task/consumer.py
actfw_core/task/isolated.py
actfw_core/task/join.py
actfw_core/task/pipe.py
actfw_core/task/producer.py
actfw_core/task/task.py
actfw_core/task/tee.py
actfw_core/unicam_isp_capture.py
actfw_core/util/pad.py
actfw_core/v4l2/__init__.py
actfw_core/v4l2/control.py
actfw_core/v4l2/types.py
actfw_core/v4l2/video.py
actfw_core-2.14.0.dist-info/LICENSE.txt
actfw_core-2.14.0.dist-info/METADATA
actfw_core-2.14.0.dist-info/WHEEL
actfw_core-2.14.0.dist-info/RECORD
