Metadata-Version: 2.1
Name: actfw-core
Version: 2.14.0
Summary: Core components of actfw, independent of specific devices
Home-page: https://github.com/Idein/actfw-core
License: MIT
Keywords: actcast
Author: Idein Inc.
Requires-Python: >=3.7,<4.0
Classifier: Development Status :: 4 - Beta
Classifier: Intended Audience :: Developers
Classifier: License :: OSI Approved :: MIT License
Classifier: Programming Language :: Python :: 3
Classifier: Programming Language :: Python :: 3.7
Classifier: Programming Language :: Python :: 3.8
Classifier: Programming Language :: Python :: 3.9
Classifier: Programming Language :: Python :: 3.10
Classifier: Programming Language :: Python :: 3.11
Classifier: Programming Language :: Python :: 3.12
Classifier: Programming Language :: Python :: 3.13
Classifier: Programming Language :: Python :: 3 :: Only
Requires-Dist: Pillow (>=5,<11)
Project-URL: Changelog, https://github.com/Idein/actfw-core/blob/master/CHANGELOG.md
Project-URL: Documentation, https://idein.github.io/actfw-core/latest/
Project-URL: Repository, https://github.com/Idein/actfw-core
